{
  "initial_capital": 1000.0,
  "cash": 1000.0,
  "positions": [],
  "closed_trades": [],
  "current_day_idx": 1,
  "last_update": "2026-06-11",
  "pending_signals": [
    {
      "ticker": "PDEX",
      "signal_date": "2026-06-11",
      "position_size_pct": 0.125,
      "trailing_stop_pct": 0.1,
      "stop_loss_pct": 0.1
    },
    {
      "ticker": "NX",
      "signal_date": "2026-06-11",
      "position_size_pct": 0.125,
      "trailing_stop_pct": 0.10647630834398238,
      "stop_loss_pct": 0.10647630834398238
    },
    {
      "ticker": "CRTO",
      "signal_date": "2026-06-11",
      "position_size_pct": 0.125,
      "trailing_stop_pct": 0.1,
      "stop_loss_pct": 0.1
    },
    {
      "ticker": "PLPC",
      "signal_date": "2026-06-11",
      "position_size_pct": 0.125,
      "trailing_stop_pct": 0.1,
      "stop_loss_pct": 0.1
    },
    {
      "ticker": "HCSG",
      "signal_date": "2026-06-11",
      "position_size_pct": 0.125,
      "trailing_stop_pct": 0.1,
      "stop_loss_pct": 0.1
    },
    {
      "ticker": "TITN",
      "signal_date": "2026-06-11",
      "position_size_pct": 0.125,
      "trailing_stop_pct": 0.12135473314723344,
      "stop_loss_pct": 0.12135473314723344
    },
    {
      "ticker": "CVEO",
      "signal_date": "2026-06-11",
      "position_size_pct": 0.125,
      "trailing_stop_pct": 0.1,
      "stop_loss_pct": 0.1
    },
    {
      "ticker": "GTE",
      "signal_date": "2026-06-11",
      "position_size_pct": 0.125,
      "trailing_stop_pct": 0.1,
      "stop_loss_pct": 0.1
    }
  ],
  "cooldown_until": {},
  "max_positions": 8,
  "holding_period_days": 20,
  "commission_bps": 5.0,
  "slippage_bps": 10.0,
  "cooldown_days": 5
}